[
      {
         "Name"   : "Half Life 2",
         "Release": "16 November 2004",
         "Score"  : "96",
         "Info"   : "Action, Shooter, Shooter, First-Person, Sci-Fi, Sci-Fi, Arcade",
         "Cost"   : "$9.99",
	 "Image"  : "https://github.com/YeLoTa/Games/blob/main/half%20life.jpg"	
      },
      {
         "Name"   : "Grand Theft Auto 5",
         "Release": "13 April 2015",
         "Score"  : "96",
         "Info"   : "Modern, Action Adventure, Open-World",
         "Cost"   : "$59.99",
	 "Image"  : "https://github.com/YeLoTa/Games/blob/main/gta%205.jpg"	
      },
      {
         "Name"   : "Bioshock",
         "Release": "21 August 2007",
         "Score"  : "96",
         "Info"   : "Action, Shooter, Shooter, First-Person, Sci-Fi, Sci-Fi, Arcade",
         "Cost"   : "$19.99",
	 "Image"  : "https://github.com/YeLoTa/Games/blob/main/bioshock.jpg"
      },
      {
         "Name"   : "Baldur's Gate 2: Shadows of Amn",
         "Release": "24 September",
         "Score"  : "95",
         "Info"   : "Role-Playing, PC-style RPG, PC-style RPG, Western-Style",
         "Cost"   : "$19.99",
	 "Image"  : "https://github.com/YeLoTa/Games/blob/main/baldurs%20gate.jpg"
      },
      {
         "Name"   : "Portal 2",
         "Release": "18 April",
         "Score"  : "95",
         "Info"   : "Action, Shooter, Shooter, First-Person, Sci-Fi, Sci-Fi, Arcade",
         "Cost"   : "9.99",
	 "Image"  : "https://github.com/YeLoTa/Games/blob/main/Portal%202.jpg"
      }
   ]
